pulsarpy_dx/__init__.py
pulsarpy_dx/utils.py
pulsarpy_dx/scripts/__init__.py
pulsarpy_dx/scripts/import_seq_results.py
pulsarpy_dx/scripts/send_mail_if_script_norun.py
pulsarpy_dx-0.5.1.data/scripts/import_seq_results.py
pulsarpy_dx-0.5.1.data/scripts/send_mail_if_script_norun.py
pulsarpy_dx-0.5.1.dist-info/LICENSE
pulsarpy_dx-0.5.1.dist-info/METADATA
pulsarpy_dx-0.5.1.dist-info/WHEEL
pulsarpy_dx-0.5.1.dist-info/top_level.txt
pulsarpy_dx-0.5.1.dist-info/RECORD
