Metadata-Version: 2.1
Name: pulsarpy-dx
Version: 0.5.1
Summary: A client for Pulsar LIMS that integrates sequencing results from DNAnexus
Home-page: https://github.com/StanfordBioinformatics/pulsarpy_dx/wiki
Author: Nathaniel Watson
Author-email: nathankw@stanford.edu
License: UNKNOWN
Project-URL: Read the Docs, https://pulsarpy_dx.readthedocs.io/en/latest
Platform: UNKNOWN
Classifier: Programming Language :: Python :: 3
Classifier: License :: OSI Approved :: MIT License
Classifier: Operating System :: OS Independent
Requires-Dist: boto3
Requires-Dist: dxpy3
Requires-Dist: pulsarpy
Requires-Dist: requests
Requires-Dist: scgpm-seqresults-dnanexus
